{
  "planets": [
    {
      "orbit": 1,
      "type": "terrestrial",
      "habitability": 0,
      "homeworld": false,
      "deposits": [
        { "resource": "gold", "yield_pct": 2, "quantity_remaining": 812298 },
        { "resource": "fuel", "yield_pct": 23, "quantity_remaining": 8877824 },
        { "resource": "fuel", "yield_pct": 24, "quantity_remaining": 26252643 },
        { "resource": "fuel", "yield_pct": 25, "quantity_remaining": 43687618 },
        { "resource": "fuel", "yield_pct": 29, "quantity_remaining": 23620916 },
        { "resource": "metallics", "yield_pct": 26, "quantity_remaining": 4723770 },
        { "resource": "metallics", "yield_pct": 31, "quantity_remaining": 93175454 },
        { "resource": "metallics", "yield_pct": 36, "quantity_remaining": 8021946 },
        { "resource": "non_metallics", "yield_pct": 24, "quantity_remaining": 19979697 },
        { "resource": "non_metallics", "yield_pct": 28, "quantity_remaining": 8142084 },
        { "resource": "non_metallics", "yield_pct": 28, "quantity_remaining": 13815884 },
        { "resource": "non_metallics", "yield_pct": 30, "quantity_remaining": 89915239 },
        { "resource": "non_metallics", "yield_pct": 31, "quantity_remaining": 5967316 },
        { "resource": "non_metallics", "yield_pct": 32, "quantity_remaining": 72052704 },
        { "resource": "non_metallics", "yield_pct": 34, "quantity_remaining": 27770052 },
        { "resource": "non_metallics", "yield_pct": 34, "quantity_remaining": 94397123 },
        { "resource": "non_metallics", "yield_pct": 36, "quantity_remaining": 43808080 },
        { "resource": "non_metallics", "yield_pct": 36, "quantity_remaining": 80648469 },
        { "resource": "non_metallics", "yield_pct": 38, "quantity_remaining": 7821412 },
        { "resource": "non_metallics", "yield_pct": 39, "quantity_remaining": 50669724 },
        { "resource": "non_metallics", "yield_pct": 41, "quantity_remaining": 35285145 },
        { "resource": "non_metallics", "yield_pct": 41, "quantity_remaining": 59235768 },
        { "resource": "non_metallics", "yield_pct": 41, "quantity_remaining": 89723339 },
        { "resource": "non_metallics", "yield_pct": 45, "quantity_remaining": 59391330 },
        { "resource": "non_metallics", "yield_pct": 46, "quantity_remaining": 90112100 }
      ]
    },
    {
      "orbit": 4,
      "type": "terrestrial",
      "habitability": 8,
      "homeworld": false,
      "deposits": [
        { "resource": "fuel", "yield_pct": 36, "quantity_remaining": 86206833 },
        { "resource": "fuel", "yield_pct": 49, "quantity_remaining": 81887431 },
        { "resource": "fuel", "yield_pct": 50, "quantity_remaining": 38499812 },
        { "resource": "fuel", "yield_pct": 54, "quantity_remaining": 54980807 },
        { "resource": "fuel", "yield_pct": 65, "quantity_remaining": 44370107 },
        { "resource": "metallics", "yield_pct": 40, "quantity_remaining": 86760209 },
        { "resource": "metallics", "yield_pct": 41, "quantity_remaining": 70710818 },
        { "resource": "metallics", "yield_pct": 48, "quantity_remaining": 8405119 },
        { "resource": "metallics", "yield_pct": 57, "quantity_remaining": 57074513 },
        { "resource": "non_metallics", "yield_pct": 35, "quantity_remaining": 46913254 },
        { "resource": "non_metallics", "yield_pct": 36, "quantity_remaining": 3943573 },
        { "resource": "non_metallics", "yield_pct": 37, "quantity_remaining": 36136789 },
        { "resource": "non_metallics", "yield_pct": 39, "quantity_remaining": 45860723 },
        { "resource": "non_metallics", "yield_pct": 44, "quantity_remaining": 70042488 },
        { "resource": "non_metallics", "yield_pct": 45, "quantity_remaining": 67551598 },
        { "resource": "non_metallics", "yield_pct": 45, "quantity_remaining": 85063987 },
        { "resource": "non_metallics", "yield_pct": 46, "quantity_remaining": 58911927 },
        { "resource": "non_metallics", "yield_pct": 48, "quantity_remaining": 95871914 },
        { "resource": "non_metallics", "yield_pct": 50, "quantity_remaining": 10971131 },
        { "resource": "non_metallics", "yield_pct": 51, "quantity_remaining": 14741082 },
        { "resource": "non_metallics", "yield_pct": 52, "quantity_remaining": 86539493 },
        { "resource": "non_metallics", "yield_pct": 54, "quantity_remaining": 67007885 },
        { "resource": "non_metallics", "yield_pct": 55, "quantity_remaining": 18945183 }
      ]
    },
    {
      "orbit": 5,
      "type": "terrestrial",
      "habitability": 25,
      "homeworld": true,
      "deposits": [
        { "resource": "gold", "yield_pct": 1, "quantity_remaining": 30000000 },
        { "resource": "fuel", "yield_pct": 9, "quantity_remaining": 99999999 },
        { "resource": "metallics", "yield_pct": 29, "quantity_remaining": 99999999 },
        { "resource": "non_metallics", "yield_pct": 29, "quantity_remaining": 99999999 }
      ]
    },
    {
      "orbit": 7,
      "type": "asteroid",
      "habitability": 0,
      "homeworld": false,
      "deposits": [
        { "resource": "gold", "yield_pct": 3, "quantity_remaining": 1405495 },
        { "resource": "fuel", "yield_pct": 9, "quantity_remaining": 30645094 },
        { "resource": "fuel", "yield_pct": 13, "quantity_remaining": 26996244 },
        { "resource": "fuel", "yield_pct": 15, "quantity_remaining": 18986269 },
        { "resource": "metallics", "yield_pct": 4, "quantity_remaining": 4452736 },
        { "resource": "metallics", "yield_pct": 4, "quantity_remaining": 50949592 },
        { "resource": "metallics", "yield_pct": 7, "quantity_remaining": 90870441 },
        { "resource": "metallics", "yield_pct": 8, "quantity_remaining": 81358516 },
        { "resource": "metallics", "yield_pct": 10, "quantity_remaining": 39310904 },
        { "resource": "metallics", "yield_pct": 10, "quantity_remaining": 95575295 },
        { "resource": "metallics", "yield_pct": 11, "quantity_remaining": 52038150 },
        { "resource": "metallics", "yield_pct": 11, "quantity_remaining": 59045424 },
        { "resource": "metallics", "yield_pct": 12, "quantity_remaining": 72238993 },
        { "resource": "metallics", "yield_pct": 12, "quantity_remaining": 77063288 },
        { "resource": "metallics", "yield_pct": 12, "quantity_remaining": 79296002 },
        { "resource": "metallics", "yield_pct": 14, "quantity_remaining": 54737672 },
        { "resource": "metallics", "yield_pct": 15, "quantity_remaining": 38335637 },
        { "resource": "metallics", "yield_pct": 15, "quantity_remaining": 45974951 },
        { "resource": "metallics", "yield_pct": 16, "quantity_remaining": 65672343 },
        { "resource": "metallics", "yield_pct": 17, "quantity_remaining": 31380994 },
        { "resource": "metallics", "yield_pct": 17, "quantity_remaining": 75425592 },
        { "resource": "metallics", "yield_pct": 18, "quantity_remaining": 7314258 },
        { "resource": "metallics", "yield_pct": 18, "quantity_remaining": 17686953 },
        { "resource": "metallics", "yield_pct": 18, "quantity_remaining": 33129078 },
        { "resource": "metallics", "yield_pct": 18, "quantity_remaining": 54431737 },
        { "resource": "metallics", "yield_pct": 18, "quantity_remaining": 93269034 },
        { "resource": "metallics", "yield_pct": 19, "quantity_remaining": 74128427 },
        { "resource": "metallics", "yield_pct": 19, "quantity_remaining": 90358118 },
        { "resource": "metallics", "yield_pct": 20, "quantity_remaining": 38191166 },
        { "resource": "metallics", "yield_pct": 20, "quantity_remaining": 64439956 },
        { "resource": "metallics", "yield_pct": 21, "quantity_remaining": 52837572 },
        { "resource": "metallics", "yield_pct": 22, "quantity_remaining": 40956149 }
      ]
    },
    {
      "orbit": 9,
      "type": "asteroid",
      "habitability": 0,
      "homeworld": false,
      "deposits": [
        { "resource": "fuel", "yield_pct": 9, "quantity_remaining": 61512112 },
        { "resource": "fuel", "yield_pct": 15, "quantity_remaining": 60895962 },
        { "resource": "metallics", "yield_pct": 4, "quantity_remaining": 21234489 },
        { "resource": "metallics", "yield_pct": 7, "quantity_remaining": 87801197 },
        { "resource": "metallics", "yield_pct": 7, "quantity_remaining": 93891983 },
        { "resource": "metallics", "yield_pct": 10, "quantity_remaining": 3430156 },
        { "resource": "metallics", "yield_pct": 11, "quantity_remaining": 75655928 },
        { "resource": "metallics", "yield_pct": 12, "quantity_remaining": 68364123 },
        { "resource": "metallics", "yield_pct": 12, "quantity_remaining": 68496410 },
        { "resource": "metallics", "yield_pct": 15, "quantity_remaining": 66433103 },
        { "resource": "metallics", "yield_pct": 16, "quantity_remaining": 51998588 },
        { "resource": "metallics", "yield_pct": 18, "quantity_remaining": 48539623 },
        { "resource": "metallics", "yield_pct": 22, "quantity_remaining": 29275178 },
        { "resource": "metallics", "yield_pct": 25, "quantity_remaining": 73533942 }
      ]
    },
    {
      "orbit": 10,
      "type": "gas_giant",
      "habitability": 0,
      "homeworld": false,
      "deposits": [
        { "resource": "fuel", "yield_pct": 16, "quantity_remaining": 44352429 },
        { "resource": "metallics", "yield_pct": 30, "quantity_remaining": 81001569 },
        { "resource": "metallics", "yield_pct": 33, "quantity_remaining": 31483298 },
        { "resource": "metallics", "yield_pct": 36, "quantity_remaining": 20533034 },
        { "resource": "non_metallics", "yield_pct": 28, "quantity_remaining": 96280806 },
        { "resource": "non_metallics", "yield_pct": 30, "quantity_remaining": 14428576 },
        { "resource": "non_metallics", "yield_pct": 30, "quantity_remaining": 27044383 },
        { "resource": "non_metallics", "yield_pct": 33, "quantity_remaining": 21727067 },
        { "resource": "non_metallics", "yield_pct": 36, "quantity_remaining": 36707769 },
        { "resource": "non_metallics", "yield_pct": 45, "quantity_remaining": 53991102 },
        { "resource": "non_metallics", "yield_pct": 46, "quantity_remaining": 4077914 }
      ]
    }
  ]
}
